fastapi_commons_exceptions/__init__.py
fastapi_commons_exceptions/authentication_failed.py
fastapi_commons_exceptions/invalid_extension.py
fastapi_commons_exceptions/invalid_session.py
fastapi_commons_exceptions/not_authenticated.py
fastapi_commons_exceptions/not_found.py
fastapi_commons_exceptions/permission_denied.py
fastapi_commons_exceptions/too_many_request.py
fastapi_commons_exceptions/validation_error.py
fastapi_commons_exceptions-0.1.1.dist-info/METADATA
fastapi_commons_exceptions-0.1.1.dist-info/WHEEL
fastapi_commons_exceptions-0.1.1.dist-info/RECORD
