Metadata-Version: 2.1
Name: fastapi-commons-exceptions
Version: 0.1.1
Summary: 
Author: ventura94
Author-email: arianventura94@gmail.com
Requires-Python: >=3.11,<4.0
Classifier: Programming Language :: Python :: 3
Classifier: Programming Language :: Python :: 3.11
Requires-Dist: fastapi (>=0.95.0,<0.96.0)
